sektorsim/__init__.py
sektorsim/a.py
sektorsim/b.py
sektorsim/tests/__init__.py
sektorsim/tests/test_sektorsim.py
sektorsim-0.0.1.dist-info/licenses/LICENSE
sektorsim-0.0.1.dist-info/METADATA
sektorsim-0.0.1.dist-info/WHEEL
sektorsim-0.0.1.dist-info/top_level.txt
sektorsim-0.0.1.dist-info/RECORD
